scraper_util_avliu/__init__.py
scraper_util_avliu/util.py
scraper_util_avliu-0.1.18.dist-info/LICENSE
scraper_util_avliu-0.1.18.dist-info/METADATA
scraper_util_avliu-0.1.18.dist-info/WHEEL
scraper_util_avliu-0.1.18.dist-info/top_level.txt
scraper_util_avliu-0.1.18.dist-info/RECORD
