Metadata-Version: 2.1
Name: scraper-util-avliu
Version: 0.1.18
License-File: LICENSE
Requires-Dist: beautifulsoup4 ==4.12.2
Requires-Dist: urllib3 ==2.0.7
Requires-Dist: botocore ==1.31.68
Requires-Dist: selenium ==4.14.0
Requires-Dist: mysql-connector ==2.2.9
Requires-Dist: undetected-chromedriver ==3.5.3
Requires-Dist: boto3 ==1.28.68
